hexdropper/__init__.py
hexdropper/create_color_image.py
hexdropper/most_common_rgb.py
hexdropper/read_image.py
hexdropper/rgb_to_hex.py
hexdropper-0.0.8.dist-info/LICENSE
hexdropper-0.0.8.dist-info/METADATA
hexdropper-0.0.8.dist-info/WHEEL
hexdropper-0.0.8.dist-info/RECORD
