Metadata-Version: 2.1
Name: hexdropper
Version: 0.0.8
Summary: Python package for determining the hex colour code given a cropped image.
License: MIT
Author: Julia Everitt
Author-email: juliaeveritt13@gmail.com
Requires-Python: >=3.9
Classifier: License :: OSI Approved :: MIT License
Classifier: Programming Language :: Python :: 3
Classifier: Programming Language :: Python :: 3.9
Classifier: Programming Language :: Python :: 3.10
Classifier: Programming Language :: Python :: 3.11
Classifier: Programming Language :: Python :: 3.12
Requires-Dist: altair (>=5.2.0)
Requires-Dist: matplotlib (>=3.8.2)
Requires-Dist: numpy (>=1.26.3)
Requires-Dist: opencv-python (>=4.9.0.80)
